uplift_kit-0.1.8.dist-info/METADATA
uplift_kit-0.1.8.dist-info/WHEEL
uplift_kit/meta.py
uplift_kit/trees.py
uplift_kit/__init__.py
uplift_kit/uplift_kit.pyd
uplift_kit-0.1.8.dist-info/RECORD
