Metadata-Version: 2.1
Name: uplift_kit
Version: 0.1.8
Classifier: Programming Language :: Rust
Classifier: Programming Language :: Python :: Implementation :: CPython
Classifier: Programming Language :: Python :: Implementation :: PyPy
Requires-Dist: pandas >= 1.0
Requires-Dist: pyarrow >= 10.0
Requires-Dist: scikit-learn
Requires-Dist: numpy
Requires-Dist: xgboost
Requires-Python: >=3.7
